Workbook

Sheet Dashboard
B2: 💰 Ultimate Budget Tracker
B3: Created: 2026-08-30 | Free open-source template
B5: Overview
B6: Total Income | C6: =SUM(Income!C:C)/2
B7: Total Expenses | C7: =SUM(Expenses!E:E)
B8: Net Balance | C8: =B6-B7
B9: Savings Rate | C9: =IF(B6>0,B8/B6,0)
B10: Monthly Budget | C10: =Settings!B2
B11: Budget Remaining | C11: =B10-B7
B14: Expense by Category
B15: Category | C15: Amount | D15: % of Total
B16: Housing | C16: =SUMIF(Expenses!C:C,"Housing",Expenses!E:E) | D16: =IF($C$23>0,C16/$C$23,0)
B17: Food | C17: =SUMIF(Expenses!C:C,"Food",Expenses!E:E) | D17: =IF($C$23>0,C17/$C$23,0)
B18: Transport | C18: =SUMIF(Expenses!C:C,"Transport",Expenses!E:E) | D18: =IF($C$23>0,C18/$C$23,0)
B19: Utilities | C19: =SUMIF(Expenses!C:C,"Utilities",Expenses!E:E) | D19: =IF($C$23>0,C19/$C$23,0)
B20: Entertainment | C20: =SUMIF(Expenses!C:C,"Entertainment",Expenses!E:E) | D20: =IF($C$23>0,C20/$C$23,0)
B21: Health | C21: =SUMIF(Expenses!C:C,"Health",Expenses!E:E) | D21: =IF($C$23>0,C21/$C$23,0)
B22: Shopping | C22: =SUMIF(Expenses!C:C,"Shopping",Expenses!E:E) | D22: =IF($C$23>0,C22/$C$23,0)
B23: Other | C23: =SUMIF(Expenses!C:C,"Other",Expenses!E:E) | D23: =IF($C$23>0,C23/$C$23,0)
B24: TOTAL | C24: =SUM(C16:C23) | D24: =SUM(D16:D23)

Sheet Income
A1: 💰 Income Tracker
A3: Date | B3: Source | C3: Amount | D3: Notes
A4: 2026-01-01 | B4: Salary | C4: 3500 | D4: Monthly paycheck
A5: 2026-01-15 | B5: Side hustle | C5: 450 | D5: Freelance design
A6: 2026-02-01 | B6: Salary | C6: 3500 | D6: Monthly paycheck
A7: 2026-02-20 | B7: Investment | C7: 120 | D7: Dividends

Sheet Expenses
A1: 💸 Expense Tracker
A3: Date | B3: Description | C3: Category | D3: Payment Method | E3: Amount | F3: Notes
A4: 2026-01-03 | B4: Rent | C4: Housing | D4: Bank | E4: 1200 | F4: Monthly rent
A5: 2026-01-05 | B5: Grocery run | C5: Food | D5: Card | E5: 180 | F5: Weekly groceries
A6: 2026-01-07 | B6: Gas | C6: Transport | D6: Card | E6: 45 | F6: Fill up
A7: 2026-01-10 | B7: Electric bill | C7: Utilities | D7: Bank | E7: 85 | F7: Monthly
A8: 2026-01-12 | B8: Movie night | C8: Entertainment | D8: Cash | E8: 30 | F8: Date night
A9: 2026-01-15 | B9: Gym membership | C9: Health | D9: Card | E9: 35 | F9: Monthly
A10: 2026-01-20 | B10: New shoes | C10: Shopping | D10: Card | E10: 75 | F10: Running shoes
A11: 2026-02-03 | B11: Rent | C11: Housing | D11: Bank | E11: 1200 | F11: Monthly rent
A12: 2026-02-05 | B12: Grocery run | C12: Food | D12: Card | E12: 195 | F12: Weekly groceries
A13: 2026-02-07 | B13: Gas | C13: Transport | D13: Card | E13: 42 | F13: Fill up

Sheet Savings Goals
A1: 🎯 Savings Goals
A3: Goal | B3: Target Amount | C3: Saved So Far | D3: Remaining | E3: Progress % | F3: Target Date
A4: Emergency Fund | B4: 10000 | C4: 3500 | D4: =B4-C4 | E4: =IF(B4>0,C4/B4,0) | F4: 2026-12-31
A5: Vacation | B5: 3000 | C5: 850 | D5: =B5-C5 | E5: =IF(B5>0,C5/B5,0) | F5: 2026-06-01
A6: New Laptop | B6: 2000 | C6: 1500 | D6: =B6-C6 | E6: =IF(B6>0,C6/B6,0) | F6: 2026-03-15
A7: House Down Payment | B7: 50000 | C7: 8500 | D7: =B7-C7 | E7: =IF(B7>0,C7/B7,0) | F7: 2027-06-01

Sheet Settings
A1: ⚙️ Settings
A3: Monthly Budget Limit | B3: 3000
A4: Currency | B4: USD
A5: Start of Month | B5: 1

Sheet Monthly Summary
A1: 📊 Monthly Summary
A3: Month | B3: Income | C3: Expenses | D3: Savings | E3: Savings %
A4: Jan | B4: =SUMIFS(Income!C:C,Income!A:A,"2026-01*") | C4: =SUMIFS(Expenses!E:E,Expenses!A:A,"2026-01*") | D4: =B4-C4 | E4: =IF(B4>0,D4/B4,0)
A5: Feb | B5: =SUMIFS(Income!C:C,Income!A:A,"2026-02*") | C5: =SUMIFS(Expenses!E:E,Expenses!A:A,"2026-02*") | D5: =B5-C5 | E5: =IF(B5>0,D5/B5,0)
A6: Mar | B6: =SUMIFS(Income!C:C,Income!A:A,"2026-03*") | C6: =SUMIFS(Expenses!E:E,Expenses!A:A,"2026-03*") | D6: =B6-C6 | E6: =IF(B6>0,D6/B6,0)
A7: Apr | B7: =SUMIFS(Income!C:C,Income!A:A,"2026-04*") | C7: =SUMIFS(Expenses!E:E,Expenses!A:A,"2026-04*") | D7: =B7-C7 | E7: =IF(B7>0,D7/B7,0)
A8: May | B8: =SUMIFS(Income!C:C,Income!A:A,"2026-05*") | C8: =SUMIFS(Expenses!E:E,Expenses!A:A,"2026-05*") | D8: =B8-C8 | E8: =IF(B8>0,D8/B8,0)
A9: Jun | B9: =SUMIFS(Income!C:C,Income!A:A,"2026-06*") | C9: =SUMIFS(Expenses!E:E,Expenses!A:A,"2026-06*") | D9: =B9-C9 | E9: =IF(B9>0,D9/B9,0)
A10: Jul | B10: =SUMIFS(Income!C:C,Income!A:A,"2026-07*") | C10: =SUMIFS(Expenses!E:E,Expenses!A:A,"2026-07*") | D10: =B10-C10 | E10: =IF(B10>0,D10/B10,0)
A11: Aug | B11: =SUMIFS(Income!C:C,Income!A:A,"2026-08*") | C11: =SUMIFS(Expenses!E:E,Expenses!A:A,"2026-08*") | D11: =B11-C11 | E11: =IF(B11>0,D11/B11,0)
A12: Sep | B12: =SUMIFS(Income!C:C,Income!A:A,"2026-09*") | C12: =SUMIFS(Expenses!E:E,Expenses!A:A,"2026-09*") | D12: =B12-C12 | E12: =IF(B12>0,D12/B12,0)
A13: Oct | B13: =SUMIFS(Income!C:C,Income!A:A,"2026-10*") | C13: =SUMIFS(Expenses!E:E,Expenses!A:A,"2026-10*") | D13: =B13-C13 | E13: =IF(B13>0,D13/B13,0)
A14: Nov | B14: =SUMIFS(Income!C:C,Income!A:A,"2026-11*") | C14: =SUMIFS(Expenses!E:E,Expenses!A:A,"2026-11*") | D14: =B14-C14 | E14: =IF(B14>0,D14/B14,0)
A15: Dec | B15: =SUMIFS(Income!C:C,Income!A:A,"2026-12*") | C15: =SUMIFS(Expenses!E:E,Expenses!A:A,"2026-12*") | D15: =B15-C15 | E15: =IF(B15>0,D15/B15,0)
